{
  "id": "users-bl",
  "name": "users business logic",
  "provides": [
    {
      "id": "users-bl",
      "version": "1.0",
      "handlers": [
        {
          "methods": ["GET"],
          "pathPattern": "/bl-users",
          "permissionsRequired": ["users-bl.collection.get"],
          "modulePermissions": ["users.collection.get"]
        },
	{
          "methods" : [ "GET" ],
          "pathPattern" : "/bl-users/_self",
          "permissionsRequired" : [],
	  "modulePermissions": ["users.item.get", "users.collection.get",
            "perms.users.get",
            "usergroups.item.get"]
	},
	{
	  "methods" : [ "POST" ],
	  "pathPattern" : "/bl-users/login",
          "permissionsRequired" : [],
          "modulePermissions" : [ "users.item.get", "users.collection.get",
            "perms.users.item.get", "perms.users.get", "usergroups.item.get" ]
	},
        {
          "methods": ["GET"],
          "pathPattern": "/bl-users/by-username/{id}",
          "permissionsRequired": ["users-bl.item.get", "perms.users.get"],
          "modulePermissions": ["users.item.get", "users.collection.get",
            "perms.users.get",
            "login.item.get"]
        },
 	{
          "methods": ["GET"],
          "pathPattern": "/bl-users/by-id/{id}",
          "permissionsRequired": ["users-bl.item.get", "perms.users.get"],
          "modulePermissions": ["users.item.get", "users.collection.get",
            "perms.users.get", "login.item.get"]
        },
	{
          "methods": ["POST"],
          "pathPattern": "/bl-users",
          "permissionsRequired": ["users-bl.item.post"],
          "permissionsDesired": ["perms.users.item.post" ],
          "modulePermissions": ["users.item.post",
            "perms.users.item.post",
            "login.item.post"]
        }, {
          "methods": ["PUT"],
          "pathPattern": "/bl-users/{id}",
          "permissionsDesired": ["perms.users.item.put" ],
          "permissionsRequired": ["users-bl.item.put"],
          "modulePermissions": ["users.edit", "users.item.put",
            "perms.users.item.put",
            "login.item.put"]
        }
      ]
    }
  ],
  "requires" : [
    {
      "id" : "users",
      "version" : "11.0"
    },
    {
      "id" : "permissions",
      "version" : "4.0"
    },
    {
      "id" : "login",
      "version" : "3.0"
    }
  ],
  "permissionSets": [
    {
      "permissionName": "users-bl.collection.get",
      "displayName" : "users-bl collection get",
      "description" : "Get a list of composite user records"
    },
    {
      "permissionName" : "users-bl.item.get",
      "displayName" : "users-bl item get",
      "description" : "Get a single composite user record by id"
    },
    {
      "permissionName" : "users-bl.item.post",
      "displayName" : "users-bl item post",
      "description" : "Create a new composite user record"
    },
    {
      "permissionName" : "users-bl.item.put",
      "displayName" : "users-bl item put",
      "description" : "Modify a composite user record"
    },
    {
      "permissionName": "module.users.enabled",
      "displayName": "User module visible in the UI",
      "description": "Should be defined in the UIs own MD, some day"
    },
    {
      "permissionName": "users-bl.view",
      "displayName": "Can view user profile",
      "description": "Some subperms can be deleted later when submodules use modern permission names",
      "subPermissions": ["users-bl.collection.get", "users-bl.item.get",
        "module.users.enabled",
        "users.collection.get", "users.item.get",
        "usergroups.collection.get",
        "login.item.get"],
      "visible": true
    }, {
      "permissionName": "users-bl.edit",
      "displayName": "Can edit user profile",
      "description": "Some subperms can be deleted later when bl does updates and ModulePermissions can be used",
      "subPermissions": [ "users-bl.view", "users-bl.item.put",
        "users.item.put",
        "login.item.put"],
      "visible": true
    }, {
      "permissionName": "users-bl.create",
      "displayName": "Can create new user",
      "description": "Some subperms can be deleted later when bl does updates and ModulePermissions can be used",
      "subPermissions": ["users-bl.edit", "users-bl.item.post",
        "users.item.post",
        "perms.users.item.post",
        "login.item.post"],
      "visible": true
    }, {
      "permissionName": "users-bl.viewperms",
      "displayName": "Can view permissions assigned to users",
      "description": "Includes all of view",
      "subPermissions": ["users-bl.view", "perms.users.get"],
      "visible": true
    }, {
      "permissionName": "users-bl.editperms",
      "displayName": "Can assign and unassign permissions to users",
      "description": "",
      "subPermissions": ["users-bl.viewperms",
        "perms.users.item.put", "perms.users.item.post", "perms.users.item.delete"],
      "visible": true
    }, {
      "permissionName": "users-bl.editpermsets",
      "displayName": "Can create, edit and remove permission sets",
      "description": "This seems out of place in users-bl, maybe it belongs under perms or settings",
      "subPermissions": [
        "perms.permissions.get","perms.permissions.item.put",
        "perms.permissions.item.post", "perms.permissions.item.delete"],
      "visible": true
	
    },
    {
      "permissionName" : "users-bl.all",
      "displayName" : "users-bl all",
      "description" : "All user business-logic permissions",
      "subPermissions" : [
        "users-bl.view",
        "users-bl.edit",
        "users-bl.create",
        "users-bl.viewperms",
        "users-bl.editperms",
        "users-bl.editpermsets"
      ],
      "visible" : false
    }
  ]
}
